opendota/__init__.py
opendota-0.1.0.dist-info/DESCRIPTION.rst
opendota-0.1.0.dist-info/METADATA
opendota-0.1.0.dist-info/RECORD
opendota-0.1.0.dist-info/WHEEL
opendota-0.1.0.dist-info/metadata.json
opendota-0.1.0.dist-info/top_level.txt
