Metadata-Version: 2.0
Name: opendota
Version: 0.1.0
Summary: Thin python client for the OpenDota API
Home-page: https://github.com/anindyaspaul/pyOpenDota
Author: Anindya Sundar Paul
Author-email: anindya@anindyaspaul.com
License: GPL-3.0
Platform: UNKNOWN
